kivymd_icon_viewer.py
kivymd_icon_viewer-0.1.1.dist-info/entry_points.txt
kivymd_icon_viewer-0.1.1.dist-info/WHEEL
kivymd_icon_viewer-0.1.1.dist-info/METADATA
kivymd_icon_viewer-0.1.1.dist-info/RECORD
