Metadata-Version: 2.1
Name: kivymd-icon-viewer
Version: 0.1.1
Summary: KivyMD Icon Viewer
License: MIT
Author: Nattōsai Mitō
Author-email: flow4re2c@gmail.com
Requires-Python: >=3.8,<4.0
Classifier: License :: OSI Approved :: MIT License
Classifier: Programming Language :: Python :: 3
Classifier: Programming Language :: Python :: 3.8
Classifier: Programming Language :: Python :: 3.9
Classifier: Programming Language :: Python :: 3.10
